{"@context": "http://iiif.io/api/presentation/2/context.json","@id": "https://app.cultural.jp/iiif-collection/collections/europeana/Dialnetラ・リオハ大学書誌データベース.json","@type": "sc:Collection","label": "Dialnetラ・リオハ大学書誌データベース (1)","manifests": [{"@id": "https://iiif.europeana.eu/presentation/9200362/BibliographicResource_3000099940405/manifest","@type": "sc:Manifest","label": "'Real english' in Japan team teachers' views on nativeness in language teaching","license": "http://rightsstatements.org/vocab/InC/1.0/","thumbnail": "https://api.europeana.eu/api/v2/thumbnail-by-url.json?uri=http%3A%2F%2Fdialnet.unirioja.es%2Frecursos%2Fimagen%3Fentidad%3DREVISTA%26tipo_contenido%3D65%26revista%3D780&type=TEXT"}],"vhint": "use-thumb"}