{"@context": "http://iiif.io/api/presentation/2/context.json","@id": "https://app.cultural.jp/iiif-collection/collections/europeana/ペンシルベニア州立大学.json","@type": "sc:Collection","label": "ペンシルベニア州立大学 (1)","manifests": [{"@id": "http://iiif.archivelab.org/iiif/proceedingsoffir00usja/manifest.json","@type": "sc:Manifest","label": "Proceedings of the first U.S.-Japan Meeting on Aquaculture at Tokyo, Japan, October 18-19, 1971 : ...","license": "http://rightsstatements.org/vocab/InC/1.0/","thumbnail": "https://api.europeana.eu/api/v2/thumbnail-by-url.json?uri=http%3A%2F%2Fiiif.archivelab.org%2Fiiif%2Fproceedingsoffir00usja%241%2Ffull%2Ffull%2F0%2Fdefault.jpg&type=TEXT"}],"vhint": "use-thumb"}