{"@context": "http://iiif.io/api/presentation/2/context.json","@id": "https://app.cultural.jp/iiif-collection/collections/europeana/マールテン・ファン・ロッセム美術館.json","@type": "sc:Collection","label": "マールテン・ファン・ロッセム美術館 (1)","manifests": [{"@id": "https://iiif.europeana.eu/presentation/2021648/0244_6962/manifest","@type": "sc:Manifest","label": "Bijzonder is, dat de houtsnede deel uitmaakt van de nalatens... (gen. from descr)","license": "http://creativecommons.org/licenses/by/3.0/","thumbnail": "https://api.europeana.eu/api/v2/thumbnail-by-url.json?uri=http%3A%2F%2Figem.adlibsoft.com%2Fwwwopacx%2Fwwwopac.ashx%3Fcommand%3Dgetcontent%26server%3Dimages%26value%3Dmvr%255C6962.jpg&type=IMAGE"}],"vhint": "use-thumb"}