{"@context": "http://iiif.io/api/presentation/2/context.json","@id": "https://app.cultural.jp/iiif-collection/collections/iiifman/中野三敏 (国文学研究資料館).json","@type": "sc:Collection","label": "中野三敏 (国文学研究資料館) (81)","manifests": [{"@id": "https://kotenseki.nijl.ac.jp/biblio/100265567/manifest","@type": "sc:Manifest","label": "諺鏡","license": "http://creativecommons.org/licenses/by-sa/4.0/deed.ja","thumbnail": "https://kotenseki.nijl.ac.jp/api/iiif/100265567/v4/NKNM/NKNM-00052/NKNM-00052-00000.tif/full/200,/0/default.jpg"},{"@id": "https://kotenseki.nijl.ac.jp/biblio/100265661/manifest","@type": "sc:Manifest","label": "鵬斎先生文鈔","license": "http://creativecommons.org/licenses/by-sa/4.0/deed.ja","thumbnail": "https://kotenseki.nijl.ac.jp/api/iiif/100265661/v4/NKNM/NKNM-00044/NKNM-00044-00000.tif/full/200,/0/default.jpg"},{"@id": "https://kotenseki.nijl.ac.jp/biblio/100271055/manifest","@type": "sc:Manifest","label": "初学文章并万躾方","license": "http://creativecommons.org/licenses/by-sa/4.0/deed.ja","thumbnail": "https://kotenseki.nijl.ac.jp/api/iiif/100271055/v4/NKNM/NKNM-00026/NKNM-00026-00000.tif/full/200,/0/default.jpg"},{"@id": "https://kotenseki.nijl.ac.jp/biblio/100271062/manifest","@type": "sc:Manifest","label": "日本汐路之記","license": "http://creativecommons.org/licenses/by-sa/4.0/deed.ja","thumbnail": "https://kotenseki.nijl.ac.jp/api/iiif/100271062/v4/NKNM/NKNM-00030/NKNM-00030-00000.tif/full/200,/0/default.jpg"},{"@id": "https://kotenseki.nijl.ac.jp/biblio/100271067/manifest","@type": "sc:Manifest","label": "竹斎","license": "http://creativecommons.org/licenses/by-sa/4.0/deed.ja","thumbnail": "https://kotenseki.nijl.ac.jp/api/iiif/100271067/v4/NKNM/NKNM-00032/NKNM-00032-00000.tif/full/200,/0/default.jpg"},{"@id": "https://kotenseki.nijl.ac.jp/biblio/100271069/manifest","@type": "sc:Manifest","label": "初学文章并万躾方","license": "http://creativecommons.org/licenses/by-sa/4.0/deed.ja","thumbnail": "https://kotenseki.nijl.ac.jp/api/iiif/100271069/v4/NKNM/NKNM-00034/NKNM-00034-00000.tif/full/200,/0/default.jpg"},{"@id": "https://kotenseki.nijl.ac.jp/biblio/100271235/manifest","@type": "sc:Manifest","label": "青葉和香葉","license": "http://creativecommons.org/licenses/by-sa/4.0/deed.ja","thumbnail": "https://kotenseki.nijl.ac.jp/api/iiif/100271235/v4/NKNM/NKNM-00037/NKNM-00037-00000.tif/full/200,/0/default.jpg"},{"@id": "https://kotenseki.nijl.ac.jp/biblio/100271289/manifest","@type": "sc:Manifest","label": "東藻会彙纂略","license": "http://creativecommons.org/licenses/by-sa/4.0/deed.ja","thumbnail": "https://kotenseki.nijl.ac.jp/api/iiif/100271289/v4/NKNM/NKNM-00076/NKNM-00076-00000.tif/full/200,/0/default.jpg"},{"@id": "https://kotenseki.nijl.ac.jp/biblio/100271301/manifest","@type": "sc:Manifest","label": "十寸鑑","license": "http://creativecommons.org/licenses/by-sa/4.0/deed.ja","thumbnail": "https://kotenseki.nijl.ac.jp/api/iiif/100271301/v4/NKNM/NKNM-00070/NKNM-00070-00000.tif/full/200,/0/default.jpg"},{"@id": "https://kotenseki.nijl.ac.jp/biblio/100265565/manifest","@type": "sc:Manifest","label": "老萊子","license": "http://creativecommons.org/licenses/by-sa/4.0/deed.ja","thumbnail": "https://kotenseki.nijl.ac.jp/api/iiif/100265565/v4/NKNM/NKNM-00077/NKNM-00077-00000.tif/full/200,/0/default.jpg"},{"@id": "https://kotenseki.nijl.ac.jp/biblio/100265647/manifest","@type": "sc:Manifest","label": "(no label) kotenseki-nijl-ac_biblio_100265647","license": "http://creativecommons.org/licenses/by-sa/4.0/deed.ja","thumbnail": "https://kotenseki.nijl.ac.jp/api/iiif/100265647/v4/NKNM/NKNM-00071/NKNM-00071-00000.tif/full/200,/0/default.jpg"},{"@id": "https://kotenseki.nijl.ac.jp/biblio/100266231/manifest","@type": "sc:Manifest","label": "表記","license": "http://creativecommons.org/licenses/by-sa/4.0/deed.ja","thumbnail": "https://kotenseki.nijl.ac.jp/api/iiif/100266231/v4/NKNM/NKNM-00073/NKNM-00073-00000.tif/full/200,/0/default.jpg"},{"@id": "https://kotenseki.nijl.ac.jp/biblio/100266244/manifest","@type": "sc:Manifest","label": "魚猟手引草","license": "http://creativecommons.org/licenses/by-sa/4.0/deed.ja","thumbnail": "https://kotenseki.nijl.ac.jp/api/iiif/100266244/v4/NKNM/NKNM-00082/NKNM-00082-00000.tif/full/200,/0/default.jpg"},{"@id": "https://kotenseki.nijl.ac.jp/biblio/100271020/manifest","@type": "sc:Manifest","label": "花濺涙帖","license": "http://creativecommons.org/licenses/by-sa/4.0/deed.ja","thumbnail": "https://kotenseki.nijl.ac.jp/api/iiif/100271020/v4/NKNM/NKNM-00014/NKNM-00014-00000.tif/full/200,/0/default.jpg"},{"@id": "https://kotenseki.nijl.ac.jp/biblio/100271038/manifest","@type": "sc:Manifest","label": "万国地名捷覧","license": "http://creativecommons.org/licenses/by-sa/4.0/deed.ja","thumbnail": "https://kotenseki.nijl.ac.jp/api/iiif/100271038/v4/NKNM/NKNM-00016/NKNM-00016-00000.tif/full/200,/0/default.jpg"},{"@id": "https://kotenseki.nijl.ac.jp/biblio/100271051/manifest","@type": "sc:Manifest","label": "ひそめ草","license": "http://creativecommons.org/licenses/by-sa/4.0/deed.ja","thumbnail": "https://kotenseki.nijl.ac.jp/api/iiif/100271051/v4/NKNM/NKNM-00025/NKNM-00025-00000.tif/full/200,/0/default.jpg"},{"@id": "https://kotenseki.nijl.ac.jp/biblio/100265560/manifest","@type": "sc:Manifest","label": "老境八友記","license": "http://creativecommons.org/licenses/by-sa/4.0/deed.ja","thumbnail": "https://kotenseki.nijl.ac.jp/api/iiif/100265560/v4/NKNM/NKNM-00060/NKNM-00060-00000.tif/full/200,/0/default.jpg"},{"@id": "https://kotenseki.nijl.ac.jp/biblio/100271018/manifest","@type": "sc:Manifest","label": "春窗秘辞","license": "http://creativecommons.org/licenses/by-sa/4.0/deed.ja","thumbnail": "https://kotenseki.nijl.ac.jp/api/iiif/100271018/v4/NKNM/NKNM-00012/NKNM-00012-00000.tif/full/200,/0/default.jpg"},{"@id": "https://kotenseki.nijl.ac.jp/biblio/100275808/manifest","@type": "sc:Manifest","label": "広倭本草","license": "http://creativecommons.org/licenses/by-sa/4.0/deed.ja","thumbnail": "https://kotenseki.nijl.ac.jp/api/iiif/100275808/v4/NKNM/NKNM-00085/NKNM-00085-00000.tif/full/200,/0/default.jpg"},{"@id": "https://kotenseki.nijl.ac.jp/biblio/100265563/manifest","@type": "sc:Manifest","label": "花帝堂梅百首集","license": "http://creativecommons.org/licenses/by-sa/4.0/deed.ja","thumbnail": "https://kotenseki.nijl.ac.jp/api/iiif/100265563/v4/NKNM/NKNM-00064/NKNM-00064-00000.tif/full/200,/0/default.jpg"},{"@id": "https://kotenseki.nijl.ac.jp/biblio/100266236/manifest","@type": "sc:Manifest","label": "鸚哥譜","license": "http://creativecommons.org/licenses/by-sa/4.0/deed.ja","thumbnail": "https://kotenseki.nijl.ac.jp/api/iiif/100266236/v4/NKNM/NKNM-00080/NKNM-00080-00000.tif/full/200,/0/default.jpg"},{"@id": "https://kotenseki.nijl.ac.jp/biblio/100271045/manifest","@type": "sc:Manifest","label": "絵本笑上戸","license": "http://creativecommons.org/licenses/by-sa/4.0/deed.ja","thumbnail": "https://kotenseki.nijl.ac.jp/api/iiif/100271045/v4/NKNM/NKNM-00021/NKNM-00021-00000.tif/full/200,/0/default.jpg"},{"@id": "https://kotenseki.nijl.ac.jp/biblio/100271288/manifest","@type": "sc:Manifest","label": "長崎縁起略","license": "http://creativecommons.org/licenses/by-sa/4.0/deed.ja","thumbnail": "https://kotenseki.nijl.ac.jp/api/iiif/100271288/v4/NKNM/NKNM-00075/NKNM-00075-00000.tif/full/200,/0/default.jpg"},{"@id": "https://kotenseki.nijl.ac.jp/biblio/100271060/manifest","@type": "sc:Manifest","label": "塵劫記","license": "http://creativecommons.org/licenses/by-sa/4.0/deed.ja","thumbnail": "https://kotenseki.nijl.ac.jp/api/iiif/100271060/v4/NKNM/NKNM-00029/NKNM-00029-00000.tif/full/200,/0/default.jpg"},{"@id": "https://kotenseki.nijl.ac.jp/biblio/100271247/manifest","@type": "sc:Manifest","label": "菌譜","license": "http://creativecommons.org/licenses/by-sa/4.0/deed.ja","thumbnail": "https://kotenseki.nijl.ac.jp/api/iiif/100271247/v4/NKNM/NKNM-00041/NKNM-00041-00000.tif/full/200,/0/default.jpg"},{"@id": "https://kotenseki.nijl.ac.jp/biblio/100271267/manifest","@type": "sc:Manifest","label": "窮楽書法帖","license": "http://creativecommons.org/licenses/by-sa/4.0/deed.ja","thumbnail": "https://kotenseki.nijl.ac.jp/api/iiif/100271267/v4/NKNM/NKNM-00066/NKNM-00066-00000.tif/full/200,/0/default.jpg"},{"@id": "https://kotenseki.nijl.ac.jp/biblio/100271262/manifest","@type": "sc:Manifest","label": "奈無でも十九論","license": "http://creativecommons.org/licenses/by-sa/4.0/deed.ja","thumbnail": "https://kotenseki.nijl.ac.jp/api/iiif/100271262/v4/NKNM/NKNM-00062/NKNM-00062-00000.tif/full/200,/0/default.jpg"},{"@id": "https://kotenseki.nijl.ac.jp/biblio/100266234/manifest","@type": "sc:Manifest","label": "天隠子","license": "http://creativecommons.org/licenses/by-sa/4.0/deed.ja","thumbnail": "https://kotenseki.nijl.ac.jp/api/iiif/100266234/v4/NKNM/NKNM-00079/NKNM-00079-00000.tif/full/200,/0/default.jpg"},{"@id": "https://kotenseki.nijl.ac.jp/biblio/100271019/manifest","@type": "sc:Manifest","label": "しぐれのせりふ","license": "http://creativecommons.org/licenses/by-sa/4.0/deed.ja","thumbnail": "https://kotenseki.nijl.ac.jp/api/iiif/100271019/v4/NKNM/NKNM-00013/NKNM-00013-00000.tif/full/200,/0/default.jpg"},{"@id": "https://kotenseki.nijl.ac.jp/biblio/100271043/manifest","@type": "sc:Manifest","label": "駿河台小川町図","license": "http://creativecommons.org/licenses/by-sa/4.0/deed.ja","thumbnail": "https://kotenseki.nijl.ac.jp/api/iiif/100271043/v4/NKNM/NKNM-00004/NKNM-00004-00000.tif/full/200,/0/default.jpg"},{"@id": "https://kotenseki.nijl.ac.jp/biblio/100271047/manifest","@type": "sc:Manifest","label": "詩文","license": "http://creativecommons.org/licenses/by-sa/4.0/deed.ja","thumbnail": "https://kotenseki.nijl.ac.jp/api/iiif/100271047/v4/NKNM/NKNM-00005/NKNM-00005-00000.tif/full/200,/0/default.jpg"},{"@id": "https://kotenseki.nijl.ac.jp/biblio/100271065/manifest","@type": "sc:Manifest","label": "丙午明辨","license": "http://creativecommons.org/licenses/by-sa/4.0/deed.ja","thumbnail": "https://kotenseki.nijl.ac.jp/api/iiif/100271065/v4/NKNM/NKNM-00031/NKNM-00031-00000.tif/full/200,/0/default.jpg"},{"@id": "https://kotenseki.nijl.ac.jp/biblio/100271244/manifest","@type": "sc:Manifest","label": "桃太郎手柄咄","license": "http://creativecommons.org/licenses/by-sa/4.0/deed.ja","thumbnail": "https://kotenseki.nijl.ac.jp/api/iiif/100271244/v4/NKNM/NKNM-00039/NKNM-00039-00000.tif/full/200,/0/default.jpg"},{"@id": "https://kotenseki.nijl.ac.jp/biblio/100271250/manifest","@type": "sc:Manifest","label": "(no label) kotenseki-nijl-ac_biblio_100271250","license": "http://creativecommons.org/licenses/by-sa/4.0/deed.ja","thumbnail": "https://kotenseki.nijl.ac.jp/api/iiif/100271250/v4/NKNM/NKNM-00043/NKNM-00043-00000.tif/full/200,/0/default.jpg"},{"@id": "https://kotenseki.nijl.ac.jp/biblio/100271254/manifest","@type": "sc:Manifest","label": "吉原一切鏡","license": "http://creativecommons.org/licenses/by-sa/4.0/deed.ja","thumbnail": "https://kotenseki.nijl.ac.jp/api/iiif/100271254/v4/NKNM/NKNM-00048/NKNM-00048-00000.tif/full/200,/0/default.jpg"},{"@id": "https://kotenseki.nijl.ac.jp/biblio/100271275/manifest","@type": "sc:Manifest","label": "(no label) kotenseki-nijl-ac_biblio_100271275","license": "http://creativecommons.org/licenses/by-sa/4.0/deed.ja","thumbnail": "https://kotenseki.nijl.ac.jp/api/iiif/100271275/v4/NKNM/NKNM-00036/NKNM-00036-00000.tif/full/200,/0/default.jpg"},{"@id": "https://kotenseki.nijl.ac.jp/biblio/100266232/manifest","@type": "sc:Manifest","label": "読詩要領","license": "http://creativecommons.org/licenses/by-sa/4.0/deed.ja","thumbnail": "https://kotenseki.nijl.ac.jp/api/iiif/100266232/v4/NKNM/NKNM-00074/NKNM-00074-00000.tif/full/200,/0/default.jpg"},{"@id": "https://kotenseki.nijl.ac.jp/biblio/100266247/manifest","@type": "sc:Manifest","label": "葫蘆市","license": "http://creativecommons.org/licenses/by-sa/4.0/deed.ja","thumbnail": "https://kotenseki.nijl.ac.jp/api/iiif/100266247/v4/NKNM/NKNM-00084/NKNM-00084-00000.tif/full/200,/0/default.jpg"},{"@id": "https://kotenseki.nijl.ac.jp/biblio/100271256/manifest","@type": "sc:Manifest","label": "観海集","license": "http://creativecommons.org/licenses/by-sa/4.0/deed.ja","thumbnail": "https://kotenseki.nijl.ac.jp/api/iiif/100271256/v4/NKNM/NKNM-00053/NKNM-00053-00000.tif/full/200,/0/default.jpg"},{"@id": "https://kotenseki.nijl.ac.jp/biblio/100271257/manifest","@type": "sc:Manifest","label": "勧善桜姫伝","license": "http://creativecommons.org/licenses/by-sa/4.0/deed.ja","thumbnail": "https://kotenseki.nijl.ac.jp/api/iiif/100271257/v4/NKNM/NKNM-00055/NKNM-00055-00000.tif/full/200,/0/default.jpg"},{"@id": "https://kotenseki.nijl.ac.jp/biblio/100271259/manifest","@type": "sc:Manifest","label": "御江戸町づくし","license": "http://creativecommons.org/licenses/by-sa/4.0/deed.ja","thumbnail": "https://kotenseki.nijl.ac.jp/api/iiif/100271259/v4/NKNM/NKNM-00058/NKNM-00058-00000.tif/full/200,/0/default.jpg"},{"@id": "https://kotenseki.nijl.ac.jp/biblio/100271260/manifest","@type": "sc:Manifest","label": "鸚鵡盃","license": "http://creativecommons.org/licenses/by-sa/4.0/deed.ja","thumbnail": "https://kotenseki.nijl.ac.jp/api/iiif/100271260/v4/NKNM/NKNM-00059/NKNM-00059-00000.tif/full/200,/0/default.jpg"},{"@id": "https://kotenseki.nijl.ac.jp/biblio/100265564/manifest","@type": "sc:Manifest","label": "奇観名話","license": "http://creativecommons.org/licenses/by-sa/4.0/deed.ja","thumbnail": "https://kotenseki.nijl.ac.jp/api/iiif/100265564/v4/NKNM/NKNM-00069/NKNM-00069-00000.tif/full/200,/0/default.jpg"},{"@id": "https://kotenseki.nijl.ac.jp/biblio/100265655/manifest","@type": "sc:Manifest","label": "(no label) kotenseki-nijl-ac_biblio_100265655","license": "http://creativecommons.org/licenses/by-sa/4.0/deed.ja","thumbnail": "https://kotenseki.nijl.ac.jp/api/iiif/100265655/v4/NKNM/NKNM-00049/NKNM-00049-00000.tif/full/200,/0/default.jpg"},{"@id": "https://kotenseki.nijl.ac.jp/biblio/100271039/manifest","@type": "sc:Manifest","label": "新訂万国全図","license": "http://creativecommons.org/licenses/by-sa/4.0/deed.ja","thumbnail": "https://kotenseki.nijl.ac.jp/api/iiif/100271039/v4/NKNM/NKNM-00003/NKNM-00003-00000.tif/full/200,/0/default.jpg"},{"@id": "https://kotenseki.nijl.ac.jp/biblio/100271048/manifest","@type": "sc:Manifest","label": "男女御土産重宝記","license": "http://creativecommons.org/licenses/by-sa/4.0/deed.ja","thumbnail": "https://kotenseki.nijl.ac.jp/api/iiif/100271048/v4/NKNM/NKNM-00022/NKNM-00022-00000.tif/full/200,/0/default.jpg"},{"@id": "https://kotenseki.nijl.ac.jp/biblio/100271056/manifest","@type": "sc:Manifest","label": "初学文章并万躾方","license": "http://creativecommons.org/licenses/by-sa/4.0/deed.ja","thumbnail": "https://kotenseki.nijl.ac.jp/api/iiif/100271056/v4/NKNM/NKNM-00027/NKNM-00027-00000.tif/full/200,/0/default.jpg"},{"@id": "https://kotenseki.nijl.ac.jp/biblio/100271058/manifest","@type": "sc:Manifest","label": "塵滴問答","license": "http://creativecommons.org/licenses/by-sa/4.0/deed.ja","thumbnail": "https://kotenseki.nijl.ac.jp/api/iiif/100271058/v4/NKNM/NKNM-00028/NKNM-00028-00000.tif/full/200,/0/default.jpg"},{"@id": "https://kotenseki.nijl.ac.jp/biblio/100271269/manifest","@type": "sc:Manifest","label": "京内まいり","license": "http://creativecommons.org/licenses/by-sa/4.0/deed.ja","thumbnail": "https://kotenseki.nijl.ac.jp/api/iiif/100271269/v4/NKNM/NKNM-00067/NKNM-00067-00000.tif/full/200,/0/default.jpg"},{"@id": "https://kotenseki.nijl.ac.jp/biblio/100271286/manifest","@type": "sc:Manifest","label": "女四書","license": "http://creativecommons.org/licenses/by-sa/4.0/deed.ja","thumbnail": "https://kotenseki.nijl.ac.jp/api/iiif/100271286/v4/NKNM/NKNM-00072/NKNM-00072-00000.tif/full/200,/0/default.jpg"},{"@id": "https://kotenseki.nijl.ac.jp/biblio/100271021/manifest","@type": "sc:Manifest","label": "本所深川細見図","license": "http://creativecommons.org/licenses/by-sa/4.0/deed.ja","thumbnail": "https://kotenseki.nijl.ac.jp/api/iiif/100271021/v4/NKNM/NKNM-00001/NKNM-00001-00000.tif/full/200,/0/default.jpg"},{"@id": "https://kotenseki.nijl.ac.jp/biblio/100271040/manifest","@type": "sc:Manifest","label": "東海漫遊稿","license": "http://creativecommons.org/licenses/by-sa/4.0/deed.ja","thumbnail": "https://kotenseki.nijl.ac.jp/api/iiif/100271040/v4/NKNM/NKNM-00017/NKNM-00017-00000.tif/full/200,/0/default.jpg"},{"@id": "https://kotenseki.nijl.ac.jp/biblio/100271041/manifest","@type": "sc:Manifest","label": "諸色染手鑑","license": "http://creativecommons.org/licenses/by-sa/4.0/deed.ja","thumbnail": "https://kotenseki.nijl.ac.jp/api/iiif/100271041/v4/NKNM/NKNM-00018/NKNM-00018-00000.tif/full/200,/0/default.jpg"},{"@id": "https://kotenseki.nijl.ac.jp/biblio/100271068/manifest","@type": "sc:Manifest","label": "七十五日","license": "http://creativecommons.org/licenses/by-sa/4.0/deed.ja","thumbnail": "https://kotenseki.nijl.ac.jp/api/iiif/100271068/v4/NKNM/NKNM-00033/NKNM-00033-00000.tif/full/200,/0/default.jpg"},{"@id": "https://kotenseki.nijl.ac.jp/biblio/100271245/manifest","@type": "sc:Manifest","label": "鈴鹿山鬼丸物語","license": "http://creativecommons.org/licenses/by-sa/4.0/deed.ja","thumbnail": "https://kotenseki.nijl.ac.jp/api/iiif/100271245/v4/NKNM/NKNM-00040/NKNM-00040-00000.tif/full/200,/0/default.jpg"},{"@id": "https://kotenseki.nijl.ac.jp/biblio/100271248/manifest","@type": "sc:Manifest","label": "残雲片水","license": "http://creativecommons.org/licenses/by-sa/4.0/deed.ja","thumbnail": "https://kotenseki.nijl.ac.jp/api/iiif/100271248/v4/NKNM/NKNM-00042/NKNM-00042-00000.tif/full/200,/0/default.jpg"},{"@id": "https://kotenseki.nijl.ac.jp/biblio/100271263/manifest","@type": "sc:Manifest","label": "寿量品/諸国経わさん","license": "http://creativecommons.org/licenses/by-sa/4.0/deed.ja","thumbnail": "https://kotenseki.nijl.ac.jp/api/iiif/100271263/v4/NKNM/NKNM-00063/NKNM-00063-00000.tif/full/200,/0/default.jpg"},{"@id": "https://kotenseki.nijl.ac.jp/biblio/100271236/manifest","@type": "sc:Manifest","label": "書画貼雑帖","license": "http://creativecommons.org/licenses/by-sa/4.0/deed.ja","thumbnail": "https://kotenseki.nijl.ac.jp/api/iiif/100271236/v4/NKNM/NKNM-00009/NKNM-00009-00000.tif/full/200,/0/default.jpg"},{"@id": "https://kotenseki.nijl.ac.jp/biblio/100271266/manifest","@type": "sc:Manifest","label": "徹透早点頭","license": "http://creativecommons.org/licenses/by-sa/4.0/deed.ja","thumbnail": "https://kotenseki.nijl.ac.jp/api/iiif/100271266/v4/NKNM/NKNM-00065/NKNM-00065-00000.tif/full/200,/0/default.jpg"},{"@id": "https://kotenseki.nijl.ac.jp/biblio/100271230/manifest","@type": "sc:Manifest","label": "池大雅和歌巻","license": "http://creativecommons.org/licenses/by-sa/4.0/deed.ja","thumbnail": "https://kotenseki.nijl.ac.jp/api/iiif/100271230/v4/NKNM/NKNM-00008/NKNM-00008-00000.tif/full/200,/0/default.jpg"},{"@id": "https://kotenseki.nijl.ac.jp/biblio/100271023/manifest","@type": "sc:Manifest","label": "役者論語","license": "http://creativecommons.org/licenses/by-sa/4.0/deed.ja","thumbnail": "https://kotenseki.nijl.ac.jp/api/iiif/100271023/v4/NKNM/NKNM-00015/NKNM-00015-00000.tif/full/200,/0/default.jpg"},{"@id": "https://kotenseki.nijl.ac.jp/biblio/100271258/manifest","@type": "sc:Manifest","label": "唐詩名花集","license": "http://creativecommons.org/licenses/by-sa/4.0/deed.ja","thumbnail": "https://kotenseki.nijl.ac.jp/api/iiif/100271258/v4/NKNM/NKNM-00057/NKNM-00057-00000.tif/full/200,/0/default.jpg"},{"@id": "https://kotenseki.nijl.ac.jp/biblio/100266230/manifest","@type": "sc:Manifest","label": "弾誓上人絵詞伝","license": "http://creativecommons.org/licenses/by-sa/4.0/deed.ja","thumbnail": "https://kotenseki.nijl.ac.jp/api/iiif/100266230/v4/NKNM/NKNM-00056/NKNM-00056-00000.tif/full/200,/0/default.jpg"},{"@id": "https://kotenseki.nijl.ac.jp/biblio/100271238/manifest","@type": "sc:Manifest","label": "蘭亭図巻","license": "http://creativecommons.org/licenses/by-sa/4.0/deed.ja","thumbnail": "https://kotenseki.nijl.ac.jp/api/iiif/100271238/v4/NKNM/NKNM-00010/NKNM-00010-00000.tif/full/200,/0/default.jpg"},{"@id": "https://kotenseki.nijl.ac.jp/biblio/100271241/manifest","@type": "sc:Manifest","label": "神明遷宮 生姜市最初","license": "http://creativecommons.org/licenses/by-sa/4.0/deed.ja","thumbnail": "https://kotenseki.nijl.ac.jp/api/iiif/100271241/v4/NKNM/NKNM-00038/NKNM-00038-00000.tif/full/200,/0/default.jpg"},{"@id": "https://kotenseki.nijl.ac.jp/biblio/100271053/manifest","@type": "sc:Manifest","label": "紋あはせ","license": "http://creativecommons.org/licenses/by-sa/4.0/deed.ja","thumbnail": "https://kotenseki.nijl.ac.jp/api/iiif/100271053/v4/NKNM/NKNM-00007/NKNM-00007-00000.tif/full/200,/0/default.jpg"},{"@id": "https://kotenseki.nijl.ac.jp/biblio/100271274/manifest","@type": "sc:Manifest","label": "鴨東新話","license": "http://creativecommons.org/licenses/by-sa/4.0/deed.ja","thumbnail": "https://kotenseki.nijl.ac.jp/api/iiif/100271274/v4/NKNM/NKNM-00068/NKNM-00068-00000.tif/full/200,/0/default.jpg"},{"@id": "https://kotenseki.nijl.ac.jp/biblio/100265557/manifest","@type": "sc:Manifest","label": "南畝帖","license": "http://creativecommons.org/licenses/by-sa/4.0/deed.ja","thumbnail": "https://kotenseki.nijl.ac.jp/api/iiif/100265557/v4/NKNM/NKNM-00054/NKNM-00054-00000.tif/full/200,/0/default.jpg"},{"@id": "https://kotenseki.nijl.ac.jp/biblio/100266241/manifest","@type": "sc:Manifest","label": "鴨東四時雑詞","license": "http://creativecommons.org/licenses/by-sa/4.0/deed.ja","thumbnail": "https://kotenseki.nijl.ac.jp/api/iiif/100266241/v4/NKNM/NKNM-00081/NKNM-00081-00000.tif/full/200,/0/default.jpg"},{"@id": "https://kotenseki.nijl.ac.jp/biblio/100271042/manifest","@type": "sc:Manifest","label": "百蟲帖","license": "http://creativecommons.org/licenses/by-sa/4.0/deed.ja","thumbnail": "https://kotenseki.nijl.ac.jp/api/iiif/100271042/v4/NKNM/NKNM-00019/NKNM-00019-00000.tif/full/200,/0/default.jpg"},{"@id": "https://kotenseki.nijl.ac.jp/biblio/100271231/manifest","@type": "sc:Manifest","label": "山王御祭礼番附","license": "http://creativecommons.org/licenses/by-sa/4.0/deed.ja","thumbnail": "https://kotenseki.nijl.ac.jp/api/iiif/100271231/v4/NKNM/NKNM-00035/NKNM-00035-00000.tif/full/200,/0/default.jpg"},{"@id": "https://kotenseki.nijl.ac.jp/biblio/100271253/manifest","@type": "sc:Manifest","label": "柳の葉末","license": "http://creativecommons.org/licenses/by-sa/4.0/deed.ja","thumbnail": "https://kotenseki.nijl.ac.jp/api/iiif/100271253/v4/NKNM/NKNM-00046/NKNM-00046-00000.tif/full/200,/0/default.jpg"},{"@id": "https://kotenseki.nijl.ac.jp/biblio/100271049/manifest","@type": "sc:Manifest","label": "十竹斎画譜","license": "http://creativecommons.org/licenses/by-sa/4.0/deed.ja","thumbnail": "https://kotenseki.nijl.ac.jp/api/iiif/100271049/v4/NKNM/NKNM-00023/NKNM-00023-00000.tif/full/200,/0/default.jpg"},{"@id": "https://kotenseki.nijl.ac.jp/biblio/100265566/manifest","@type": "sc:Manifest","label": "今日歌集","license": "http://creativecommons.org/licenses/by-sa/4.0/deed.ja","thumbnail": "https://kotenseki.nijl.ac.jp/api/iiif/100265566/v4/NKNM/NKNM-00045/NKNM-00045-00000.tif/full/200,/0/default.jpg"},{"@id": "https://kotenseki.nijl.ac.jp/biblio/100271022/manifest","@type": "sc:Manifest","label": "神田浜町日本橋北図","license": "http://creativecommons.org/licenses/by-sa/4.0/deed.ja","thumbnail": "https://kotenseki.nijl.ac.jp/api/iiif/100271022/v4/NKNM/NKNM-00002/NKNM-00002-00000.tif/full/200,/0/default.jpg"},{"@id": "https://kotenseki.nijl.ac.jp/biblio/100271261/manifest","@type": "sc:Manifest","label": "広倭本草","license": "http://creativecommons.org/licenses/by-sa/4.0/deed.ja","thumbnail": "https://kotenseki.nijl.ac.jp/api/iiif/100271261/v4/NKNM/NKNM-00061/NKNM-00061-00000.tif/full/200,/0/default.jpg"},{"@id": "https://kotenseki.nijl.ac.jp/biblio/100271246/manifest","@type": "sc:Manifest","label": "日本名所の絵","license": "http://creativecommons.org/licenses/by-sa/4.0/deed.ja","thumbnail": "https://kotenseki.nijl.ac.jp/api/iiif/100271246/v4/NKNM/NKNM-00011/NKNM-00011-00000.tif/full/200,/0/default.jpg"},{"@id": "https://kotenseki.nijl.ac.jp/biblio/100266250/manifest","@type": "sc:Manifest","label": "梅所詩稿","license": "http://creativecommons.org/licenses/by-sa/4.0/deed.ja","thumbnail": "https://kotenseki.nijl.ac.jp/api/iiif/100266250/v4/NKNM/NKNM-00047/NKNM-00047-00000.tif/full/200,/0/default.jpg"},{"@id": "https://kotenseki.nijl.ac.jp/biblio/100271044/manifest","@type": "sc:Manifest","label": "倭国風流","license": "http://creativecommons.org/licenses/by-sa/4.0/deed.ja","thumbnail": "https://kotenseki.nijl.ac.jp/api/iiif/100271044/v4/NKNM/NKNM-00020/NKNM-00020-00000.tif/full/200,/0/default.jpg"},{"@id": "https://kotenseki.nijl.ac.jp/biblio/100271255/manifest","@type": "sc:Manifest","label": "仮寝夢","license": "http://creativecommons.org/licenses/by-sa/4.0/deed.ja","thumbnail": "https://kotenseki.nijl.ac.jp/api/iiif/100271255/v4/NKNM/NKNM-00050/NKNM-00050-00000.tif/full/200,/0/default.jpg"},{"@id": "https://kotenseki.nijl.ac.jp/biblio/100271265/manifest","@type": "sc:Manifest","label": "ふもんぼん第二十五","license": "http://creativecommons.org/licenses/by-sa/4.0/deed.ja","thumbnail": "https://kotenseki.nijl.ac.jp/api/iiif/100271265/v4/NKNM/NKNM-00051/NKNM-00051-00000.tif/full/200,/0/default.jpg"}],"vhint": "use-thumb"}